swervepy/__init__.py
swervepy/abstract/__init__.py
swervepy/abstract/motor.py
swervepy/abstract/sensor.py
swervepy/abstract/system.py
swervepy/conversions.py
swervepy/impl/__init__.py
swervepy/impl/motor.py
swervepy/impl/sensor.py
swervepy/impl/system.py
swervepy/subsystem.py
swervepy/vision.py
swervepy-1.3.0.dist-info/LICENSE
swervepy-1.3.0.dist-info/METADATA
swervepy-1.3.0.dist-info/WHEEL
swervepy-1.3.0.dist-info/RECORD
